[
      {
            "name": "The Lost Symbol",
            "author": "Dan Brown"
      },
      {
            "name": "Half of a Yellow Sun",
            "author": "Chimamanda Ngozi Adichie"
      },
      {
            "name": "Atomic Habits",
            "author": "James Clear"
      },
      {
            "name": "Dune",
            "author": "Frank Herbert"
      },
      {
            "name": "Kafka on the Shore",
            "author": "Ulysses Grant"
      },
      {
            "name": "Kafka on the Shore",
            "author": "Ulysses Grant"
      }
]